noverde_serpens-2.7.4.dist-info/licenses/LICENSE
serpens/__init__.py
serpens/api.py
serpens/cache.py
serpens/cloud_storage.py
serpens/compute_engine.py
serpens/csvutils.py
serpens/database.py
serpens/document.py
serpens/elastic.py
serpens/elastic_sanitize.py
serpens/envvars.py
serpens/financial.py
serpens/initializers.py
serpens/lambda_function.py
serpens/log.py
serpens/messages.py
serpens/migrations.py
serpens/parameters.py
serpens/pubsub.py
serpens/rekognition.py
serpens/s3.py
serpens/schema.py
serpens/secrets_manager.py
serpens/sentry.py
serpens/sns.py
serpens/sqs.py
serpens/storages.py
serpens/testgres.py
serpens/validators.py
noverde_serpens-2.7.4.dist-info/METADATA
noverde_serpens-2.7.4.dist-info/WHEEL
noverde_serpens-2.7.4.dist-info/top_level.txt
noverde_serpens-2.7.4.dist-info/RECORD
