Metadata-Version: 2.4
Name: noverde-serpens
Version: 2.7.4
Summary: A set of Python utilities, recipes and snippets
Author-email: Noverde Developers <dev@noverde.com.br>
Keywords: utilities,aws
Classifier: Programming Language :: Python :: 3
Requires-Python: >=3.8
License-File: LICENSE
Dynamic: license-file
